[
  {
    "id": 1,
    "name": "노말"
  },
  {
    "id": 2,
    "name": "격투"
  },
  {
    "id": 3,
    "name": "비행"
  },
  {
    "id": 4,
    "name": "독"
  },
  {
    "id": 5,
    "name": "땅"
  },
  {
    "id": 6,
    "name": "바위"
  },
  {
    "id": 7,
    "name": "벌레"
  },
  {
    "id": 8,
    "name": "고스트"
  },
  {
    "id": 9,
    "name": "강철"
  },
  {
    "id": 10,
    "name": "불꽃"
  },
  {
    "id": 11,
    "name": "물"
  },
  {
    "id": 12,
    "name": "풀"
  },
  {
    "id": 13,
    "name": "전기"
  },
  {
    "id": 14,
    "name": "에스퍼"
  },
  {
    "id": 15,
    "name": "얼음"
  },
  {
    "id": 16,
    "name": "드래곤"
  },
  {
    "id": 17,
    "name": "악"
  },
  {
    "id": 18,
    "name": "페어리"
  }
]